jiratools/__init__.py
jiratools/auth.py
jiratools/issue.py
jiratools/jiraclient.py
jiratools/project.py
jiratools/search.py
jiratools/transitions.py
goatjiratools-2024.7.16.1623.dist-info/METADATA
goatjiratools-2024.7.16.1623.dist-info/WHEEL
goatjiratools-2024.7.16.1623.dist-info/entry_points.txt
goatjiratools-2024.7.16.1623.dist-info/top_level.txt
goatjiratools-2024.7.16.1623.dist-info/RECORD
