Metadata-Version: 2.1
Name: goatjiratools
Version: 2024.7.16.1623
Summary: jiratools - a CLI client for Jira included by default
Author-email: Chris Stacks <centerupt@gmail.com>
Classifier: Programming Language :: Python :: 3
Classifier: Operating System :: OS Independent
Requires-Python: >=3.7
Requires-Dist: click >=8.0.4
Requires-Dist: jira
Requires-Dist: tabulate
Requires-Dist: six
Requires-Dist: prompt-toolkit
